fedtoy/__init__.py
fedtoy-0.0.1a1.dist-info/LICENSE
fedtoy-0.0.1a1.dist-info/METADATA
fedtoy-0.0.1a1.dist-info/WHEEL
fedtoy-0.0.1a1.dist-info/top_level.txt
fedtoy-0.0.1a1.dist-info/RECORD
