Metadata-Version: 2.1
Name: fedtoy
Version: 0.0.1a1
Summary: 🧸FedToy: A robust deterministic federated learning simulator.
Home-page: https://github.com/beiyuouo/fedtoy
Author: Bingjie Yan
Author-email: bj.yan.pa@qq.com
Maintainer: Bingjie Yan
Maintainer-email: bj.yan.pa@qq.com
License: Apache-2.0 License
Keywords: federated learning,deep learning,pytorch,asynchronous federated learning,wandb
Classifier: Topic :: Scientific/Engineering
Classifier: Topic :: Scientific/Engineering :: Artificial Intelligence
Classifier: Topic :: Software Development
Classifier: Topic :: Software Development :: Libraries
Classifier: Topic :: Software Development :: Libraries :: Python Modules
Classifier: License :: OSI Approved :: Apache Software License
Classifier: Programming Language :: Python :: 3
Requires-Python: >=3.6
License-File: LICENSE
Requires-Dist: torch (>=1.8.2)
Requires-Dist: torchvision (>=0.9.2)
Requires-Dist: numpy
Requires-Dist: ezkfg
Requires-Dist: pyyaml
Requires-Dist: urllib3 (==1.25.3)
Requires-Dist: click
Provides-Extra: dev
Requires-Dist: pytest ; extra == 'dev'
Requires-Dist: pytest-order ; extra == 'dev'
Requires-Dist: mkdocs ; extra == 'dev'
Provides-Extra: docs
Requires-Dist: mkdocs ; extra == 'docs'
Provides-Extra: test
Requires-Dist: pytest ; extra == 'test'
Requires-Dist: pytest-order ; extra == 'test'
